corinne_greene/__init__.py
corinne_greene/__main__.py
corinne_greene/names.txt
corinne_greene/speaker.py
corinne_greene/speakers/__init__.py
corinne_greene/speakers/corinne.py
corinne_greene-0.3.0.dist-info/licenses/LICENSE.txt
corinne_greene-0.3.0.dist-info/METADATA
corinne_greene-0.3.0.dist-info/WHEEL
corinne_greene-0.3.0.dist-info/entry_points.txt
corinne_greene-0.3.0.dist-info/top_level.txt
corinne_greene-0.3.0.dist-info/RECORD
