Metadata-Version: 2.4
Name: corinne_greene
Version: 0.3.0
Summary: My first package!
Author-email: Corinne Greene <corinne.greene@thehartford.com>
Maintainer-email: Corinne Greene <corinne.greene@thehartford.com>
License: Copyright 2025 Corinne Greene
Project-URL: Homepage, https://github.com/jfuruness/justin_furuness
Project-URL: Documentation, https://github.com/jfuruness/justin_furuness/README.md
Keywords: Greene
Classifier: Programming Language :: Python :: 3.11
Classifier: Programming Language :: Python :: Implementation :: CPython
Classifier: License :: OSI Approved :: BSD License
Classifier: Intended Audience :: Developers
Classifier: Operating System :: POSIX :: Linux
Classifier: Operating System :: Microsoft :: Windows
Classifier: Operating System :: MacOS
Classifier: Operating System :: MacOS :: MacOS X
Requires-Python: >=3.11
License-File: LICENSE.txt
Requires-Dist: colorama~=0.0
Provides-Extra: test
Requires-Dist: twine; extra == "test"
Requires-Dist: build; extra == "test"
Dynamic: license-file
